and_gate.v
module and_gate(a,b,c,y);

 input a,b,c;
 output y;

 assign y = a&b&c;

endmodule

tb_and_gate.v
module tb_and_gate;
reg a,b,c;
wire y;

and_gate dut(
    .a(a),
    .b(b),
    .c(c),
    .y(y)
);

initial begin
    $dumpfile("and_gate.vcd");
    $dumpvars(0,tb_and_gate);
    $display("time | a | b | c | y");
    $display("---------------------");


    a=0; b = 0; c = 0; #10;
    $display("%4t | %b | %b | %b |%b", $time, a, b,c, y);
    a=0; b = 0; c = 1; #10;$display("%4t | %b | %b | %b |%b", $time, a, b,c, y);
    a=0; b = 1; c = 0; #10;$display("%4t | %b | %b | %b |%b", $time, a, b,c, y);
    a=0; b = 1; c = 1; #10;$display("%4t | %b | %b | %b |%b", $time, a, b,c, y);
    a=1; b = 0; c = 0; #10;$display("%4t | %b | %b | %b |%b", $time, a, b,c, y);
    a=1; b = 0; c = 1; #10;$display("%4t | %b | %b | %b |%b", $time, a, b,c, y);
    a=1; b = 1; c = 0; #10;$display("%4t | %b | %b | %b |%b", $time, a, b,c, y);
    a=1; b = 1; c = 1; #10;$display("%4t | %b | %b | %b |%b", $time, a, b,c, y);
    
end

endmodule

and_gate.vcd
$date
	Fri Dec 19 19:35:15 2025
$end
$version
	Icarus Verilog
$end
$timescale
	1s
$end
$scope module tb_and_gate $end
$var wire 1 ! y $end
$var reg 1 " a $end
$var reg 1 # b $end
$var reg 1 $ c $end
$scope module dut $end
$var wire 1 " a $end
$var wire 1 # b $end
$var wire 1 $ c $end
$var wire 1 ! y $end
$upscope $end
$upscope $end
$enddefinitions $end
$comment Show the parameter values. $end
$dumpall
$end
#0
$dumpvars
0$
0#
0"
0!
$end
#10
1$
#20
0$
1#
#30
1$
#40
0$
0#
1"
#50
1$
#60
0$
1#
#70
1!
1$
