rtl/flip_flops/d_flip_flop.v
module d_flip_flop(
    input wire clk,
    input wire reset,
    input wire d,
    output reg q
);

    always @(posedge clk) begin
        if (reset)
            q <= 0;
        else
            q <= d;
    end

endmodule

tb_d_ff.v
module tb_d_ff;
    reg clk, d, reset;
    wire q;

    d_flip_flop dut(
        .clk(clk),
        .reset(reset),
        .d(d),
        .q(q)
    );

    // Clock generation (automatic toggling)
    initial begin
        clk = 0;
        forever #5 clk = ~clk;  // Period = 10 time units
    end

    // Stimulus
    initial begin
        $dumpfile("d_flip_flop.vcd");
        $dumpvars(0, tb_d_ff);
        
        $display("Time | clk | d | reset | q");
        $display("-----|-----|---|-------|---");
        
        // Initialize
        reset = 1; d = 0;
        #10;  // Wait for clock edge
        $display("%4t |  %b  | %b |   %b   | %b", $time, clk, d, reset, q);
        
        // Release reset
        reset = 0; d = 0;
        #10;
        $display("%4t |  %b  | %b |   %b   | %b", $time, clk, d, reset, q);
        
        // Change d to 1
        d = 1;
        #10;
        $display("%4t |  %b  | %b |   %b   | %b", $time, clk, d, reset, q);
        
        // Keep d at 1
        #10;
        $display("%4t |  %b  | %b |   %b   | %b", $time, clk, d, reset, q);
        
        // Change d to 0
        d = 0;
        #10;
        $display("%4t |  %b  | %b |   %b   | %b", $time, clk, d, reset, q);
        
        // Test reset
        reset = 1;
        #10;
        $display("%4t |  %b  | %b |   %b   | %b", $time, clk, d, reset, q);
        
        $finish;
    end

endmodule

d_flip_flop.vcd
$date
	Wed Dec 24 13:07:45 2025
$end
$version
	Icarus Verilog
$end
$timescale
	1s
$end
$scope module tb_d_ff $end
$var wire 1 ! q $end
$var reg 1 " clk $end
$var reg 1 # d $end
$var reg 1 $ reset $end
$scope module dut $end
$var wire 1 " clk $end
$var wire 1 # d $end
$var wire 1 $ reset $end
$var reg 1 ! q $end
$upscope $end
$upscope $end
$enddefinitions $end
$comment Show the parameter values. $end
$dumpall
$end
#0
$dumpvars
1$
0#
0"
x!
$end
#5
0!
1"
#10
0"
0$
#15
1"
#20
0"
1#
#25
1!
1"
#30
0"
#35
1"
#40
0"
0#
#45
0!
1"
#50
0"
1$
