rtl/flip_flops/door_lock_fsm.v
module door_lock(
    input wire clk , rst,
    input wire key,
    output reg LOCK, UNLOCK
);

localparam lock = 2'b00 ;
localparam unlock = 2'b01;

reg [1:0] current_State;
reg [1:0] next_state;

always @(posedge clk or posedge rst) begin
    if(rst)
    current_State <= lock;
    else
    current_State <= next_state;
end

always @(*) begin
    case (current_State)
        lock: begin 
            if(key)
            next_state = unlock;
            else
            next_state = lock;
        end 
        unlock:begin
          if(!key)
          next_state = lock;
          else
          next_state = unlock;
        end
        default: next_state = lock; 
    endcase
end

always @(*) begin
    LOCK = 0;
    UNLOCK =0;

    case (current_State)
        lock: LOCK =1;
        unlock: UNLOCK=1;
        
    endcase
end

endmodule

tb/tb_door_lock.v
module tb_door_lock;

reg clk,rst,key;
wire LOCK,UNLOCK;

door_lock dut(
    .clk(clk),.rst(rst) , .key(key),
    .LOCK(LOCK) , .UNLOCK(UNLOCK)
);

initial begin
    clk =0;
    forever #5 clk = ~clk;
end

initial begin 
    $dumpfile("door_lock.vcd");
    $dumpvars(0,tb_door_lock);
    $display("time | rst | key | lock | unlock | state");
    $display("========================================");
    $monitor("%4t | %b |%b |%b |%b |%b |",
    $time,rst,key,LOCK,UNLOCK,dut.current_State);

    //intilize
    rst =1; key =0;
    #10;
    rst = 0; #10;

    //key inserted
    key=1; #20;
    
    //key removed
    key = 0; #20;

    //rst midway
    key = 1; #10;
    rst=1; #5;
    rst=0;
    #5;

    $finish;

end

endmodule

door_lock.vcd
$date
	Fri Apr  3 21:07:26 2026
$end
$version
	Icarus Verilog
$end
$timescale
	1s
$end
$scope module tb_door_lock $end
$var wire 1 ! UNLOCK $end
$var wire 1 " LOCK $end
$var reg 1 # clk $end
$var reg 1 $ key $end
$var reg 1 % rst $end
$scope module dut $end
$var wire 1 # clk $end
$var wire 1 $ key $end
$var wire 1 % rst $end
$var parameter 2 & lock $end
$var parameter 2 ' unlock $end
$var reg 1 " LOCK $end
$var reg 1 ! UNLOCK $end
$var reg 2 ( current_State [1:0] $end
$var reg 2 ) next_state [1:0] $end
$upscope $end
$upscope $end
$enddefinitions $end
$comment Show the parameter values. $end
$dumpall
b1 '
b0 &
$end
#0
$dumpvars
b0 )
b0 (
1%
0$
0#
1"
0!
$end
#5
1#
#10
0#
0%
#15
1#
#20
b1 )
0#
1$
#25
1!
0"
b1 (
1#
#30
0#
#35
1#
#40
b0 )
0#
0$
#45
1"
0!
b0 (
1#
#50
0#
#55
1#
#60
b1 )
0#
1$
#65
1!
0"
b1 (
1#
#70
1"
0!
b0 (
0#
1%
#75
1!
0"
b1 (
1#
0%
