rtl/sequntial/register/sipo.v
module sipo(
    input wire clk,reset,si,
    output reg [7:0] po
);
always @(posedge clk or posedge reset) begin 
    if(reset)
    po<=8'b0;
    else
    po<={po[6:0],si};
end

endmodule

tb/register/tb_sipo.v
module tb_sipo;

reg clk,reset,si;
wire [7:0] po;

sipo dut(
    .clk(clk),
    .reset(reset),
    .si(si),
    .po(po)
);

initial begin 
    clk =0;
    forever #5 clk = ~clk;
    end

    initial begin 
        $dumpfile("sipo.vcd");
        $dumpvars(0,tb_sipo);
        $display("Time | clk | rst | si | po |");
        $display("----------------------------");
        $monitor("%4t | %b | %b | %b | %b |",$time,clk,reset,si,po);

        reset = 1; si = 0; #10;

        // release reset
        reset = 0; #10;

        // shift in pattern: 10110111
        si = 1; #10;
        si = 0; #10;
        si = 1; #10;
        si = 1; #10;
        si = 0; #10;
        si = 1; #10;
        si = 1; #10;
        si = 1; #10;

        // shift in zeros to push data out
        repeat (8) begin
            si = 0; #10;
        end

        $finish;
    end

    



endmodule

sipo.vcd
$date
	Tue Feb 17 08:09:20 2026
$end
$version
	Icarus Verilog
$end
$timescale
	1s
$end
$scope module tb_sipo $end
$var wire 8 ! po [7:0] $end
$var reg 1 " clk $end
$var reg 1 # reset $end
$var reg 1 $ si $end
$scope module dut $end
$var wire 1 " clk $end
$var wire 1 # reset $end
$var wire 1 $ si $end
$var reg 8 % po [7:0] $end
$upscope $end
$upscope $end
$enddefinitions $end
$comment Show the parameter values. $end
$dumpall
$end
#0
$dumpvars
b0 %
0$
1#
0"
b0 !
$end
#5
1"
#10
0"
0#
#15
1"
#20
0"
1$
#25
b1 !
b1 %
1"
#30
0"
0$
#35
b10 !
b10 %
1"
#40
0"
1$
#45
b101 !
b101 %
1"
#50
0"
#55
b1011 !
b1011 %
1"
#60
0"
0$
#65
b10110 !
b10110 %
1"
#70
0"
1$
#75
b101101 !
b101101 %
1"
#80
0"
#85
b1011011 !
b1011011 %
1"
#90
0"
#95
b10110111 !
b10110111 %
1"
#100
0"
0$
#105
b1101110 !
b1101110 %
1"
#110
0"
#115
b11011100 !
b11011100 %
1"
#120
0"
#125
b10111000 !
b10111000 %
1"
#130
0"
#135
b1110000 !
b1110000 %
1"
#140
0"
#145
b11100000 !
b11100000 %
1"
#150
0"
#155
b11000000 !
b11000000 %
1"
#160
0"
#165
b10000000 !
b10000000 %
1"
#170
0"
#175
b0 !
b0 %
1"
