rtl/flip_flops/siso.v
module siso(
    input  wire clk,
    input  wire reset,
    input  wire si,
    output reg  so
);

    reg [7:0] shift_reg;

    always @(posedge clk or posedge reset) begin
        if (reset) begin
            shift_reg <= 8'b0;
            so        <= 1'b0;
        end else begin
            shift_reg <= {shift_reg[6:0], si}; // shift left, insert si at LSB
            so        <= shift_reg[7];          // output MSB
        end
    end

endmodule

tb/tb_siso.v
module tb_siso;

    reg clk, reset, si;
    wire so;

    siso dut(
        .clk(clk),
        .reset(reset),
        .si(si),
        .so(so)
    );

    initial begin
        clk = 0;
        forever #5 clk = ~clk;
    end

    initial begin 
        $dumpfile("siso.vcd");
        $dumpvars(0, tb_siso);
        $display("Time | clk | rst | si | so | shift_reg");
        $display("---------------------------------------");
        $monitor("%4t | %b | %b | %b | %b | %b",
                 $time, clk, reset, si, so, dut.shift_reg);

        // reset
        reset = 1; si = 0; #10;

        // release reset
        reset = 0; #10;

        // shift in pattern: 10110111
        si = 1; #10;
        si = 0; #10;
        si = 1; #10;
        si = 1; #10;
        si = 0; #10;
        si = 1; #10;
        si = 1; #10;
        si = 1; #10;

        // shift in zeros to push data out
        repeat (8) begin
            si = 0; #10;
        end

        $finish;
    end

endmodule

siso.vcd
$date
	Tue Feb 17 08:17:03 2026
$end
$version
	Icarus Verilog
$end
$timescale
	1s
$end
$scope module tb_siso $end
$var wire 1 ! so $end
$var reg 1 " clk $end
$var reg 1 # reset $end
$var reg 1 $ si $end
$scope module dut $end
$var wire 1 " clk $end
$var wire 1 # reset $end
$var wire 1 $ si $end
$var reg 8 % shift_reg [7:0] $end
$var reg 1 ! so $end
$upscope $end
$upscope $end
$enddefinitions $end
$comment Show the parameter values. $end
$dumpall
$end
#0
$dumpvars
b0 %
0$
1#
0"
0!
$end
#5
1"
#10
0"
0#
#15
1"
#20
0"
1$
#25
b1 %
1"
#30
0"
0$
#35
b10 %
1"
#40
0"
1$
#45
b101 %
1"
#50
0"
#55
b1011 %
1"
#60
0"
0$
#65
b10110 %
1"
#70
0"
1$
#75
b101101 %
1"
#80
0"
#85
b1011011 %
1"
#90
0"
#95
b10110111 %
1"
#100
0"
0$
#105
1!
b1101110 %
1"
#110
0"
#115
0!
b11011100 %
1"
#120
0"
#125
1!
b10111000 %
1"
#130
0"
#135
b1110000 %
1"
#140
0"
#145
0!
b11100000 %
1"
#150
0"
#155
1!
b11000000 %
1"
#160
0"
#165
b10000000 %
1"
#170
0"
#175
b0 %
1"
