rtl/flip_flops/sr_ff.v
module sr_ff (
    input  wire clk,
    input  wire reset,
    input  wire s,
    input  wire r,
    output reg  q,
    output reg  invalid
);

always @(posedge clk or posedge reset) begin
    if (reset) begin
        q <= 1'b0;
        invalid <= 1'b0;
    end else begin
        case ({s, r})
            2'b00: begin
                q <= q;
                invalid <= 1'b0;
            end
            2'b01: begin
                q <= 1'b0;
                invalid <= 1'b0;
            end
            2'b10: begin
                q <= 1'b1;
                invalid <= 1'b0;
            end
            2'b11: begin
                q <= 1'bx;
                invalid <= 1'b1;
            end
        endcase
    end
end

endmodule

tb/flip-flops/tb_sr_ff.v
module tb_sr_ff;

reg clk, reset, s, r;
wire q, invalid;

sr_ff dut (
    .clk(clk),
    .reset(reset),
    .s(s),
    .r(r),
    .q(q),
    .invalid(invalid)
);

initial begin
    clk = 0;
    forever #5 clk = ~clk;
end

initial begin
    $dumpfile("sr_ff.vcd");
    $dumpvars(0, tb_sr_ff);
    $display("Time | clk | rst | s | r | q | invalid");
    $display("--------------------------------------");
    $monitor("%4t |  %b  |  %b  | %b | %b | %b |    %b",
             $time, clk, reset, s, r, q, invalid);

    reset = 1; s = 0; r = 0;
    #10;
    reset = 0; #10;

    s=0; r=0; #20;   // hold
    s=0; r=1; #20;   // reset
    s=1; r=0; #20;   // set
    s=0; r=0; #20;   // hold

    $display("warning");
    s=1; r=1; #20;   // forbidden

    s=0; r=0; #20;   // recovery

    s=1; r=0; #5;
    reset=1; #10;
    reset=0; #10;

    $finish;
end

endmodule

sr_ff.vcd
$date
	Tue Jan 27 21:06:39 2026
$end
$version
	Icarus Verilog
$end
$timescale
	1s
$end
$scope module tb_sr_ff $end
$var wire 1 ! q $end
$var wire 1 " invalid $end
$var reg 1 # clk $end
$var reg 1 $ r $end
$var reg 1 % reset $end
$var reg 1 & s $end
$scope module dut $end
$var wire 1 # clk $end
$var wire 1 $ r $end
$var wire 1 % reset $end
$var wire 1 & s $end
$var reg 1 " invalid $end
$var reg 1 ! q $end
$upscope $end
$upscope $end
$enddefinitions $end
$comment Show the parameter values. $end
$dumpall
$end
#0
$dumpvars
0&
1%
0$
0#
0"
0!
$end
#5
1#
#10
0#
0%
#15
1#
#20
0#
#25
1#
#30
0#
#35
1#
#40
0#
1$
#45
1#
#50
0#
#55
1#
#60
0#
0$
1&
#65
1!
1#
#70
0#
#75
1#
#80
0#
0&
#85
1#
#90
0#
#95
1#
#100
0#
1$
1&
#105
1"
x!
1#
#110
0#
#115
1#
#120
0#
0$
0&
#125
0"
1#
#130
0#
#135
1#
#140
0#
1&
#145
0!
1#
1%
#150
0#
#155
1!
1#
0%
