rtl/flip_flops/jk_ff.v
module jk_ff(
    input  wire clk,j,reset,k,
    output reg q
);

always @(posedge clk or posedge reset) begin

    if (reset) begin
        q<=1'b0;
    end
    else begin 
        case ({j,k})
        2'b00: q<= q;
        2'b01: q<= 1'b0;
        2'b10: q<= 1'b1;
        2'b11: q<= ~q;
        endcase
    end
end


endmodule

rtl/flip_flops/t_ff_from_jk.v
module t_ff_from_jk(
    input wire clk , reset, t,
    output  wire q
);

wire j , k;

assign j = t;
assign k = t;

jk_ff jk_inst(

    .clk(clk),
    .reset(reset),
    .j(j),
    .k(k),
    .q(q)
);



endmodule

tb/tb_t_ff_from_jk.v
module tb_t_ff_from_jk;

    reg clk, reset, t;
    wire q;

    t_ff_from_jk dut(
        .clk(clk),
        .t(t),
        .reset(reset),
        .q(q)
    );

    initial begin 
        clk = 0;
        forever #5 clk = ~clk;
    end

    initial begin 
        $dumpfile("t_ff_jk.vcd");
        $dumpvars(0, tb_t_ff_from_jk);
        
        $display("time | clk | reset | t | q |");
        $display("----------------------------");
        $monitor("%4t | %b | %b | %b | %b |", $time, clk, reset, t, q);

        reset = 1; t = 0; #10;
        reset = 0; #10;

        t = 0; #20;
        t = 1; #40;
        t = 0; #20;

        $finish;
    end

endmodule

t_ff_jk.vcd
$date
	Mon Jan 19 21:46:16 2026
$end
$version
	Icarus Verilog
$end
$timescale
	1s
$end
$scope module tb_t_ff_from_jk $end
$var wire 1 ! q $end
$var reg 1 " clk $end
$var reg 1 # reset $end
$var reg 1 $ t $end
$scope module dut $end
$var wire 1 " clk $end
$var wire 1 % j $end
$var wire 1 & k $end
$var wire 1 # reset $end
$var wire 1 $ t $end
$var wire 1 ! q $end
$scope module jk_inst $end
$var wire 1 " clk $end
$var wire 1 % j $end
$var wire 1 & k $end
$var wire 1 # reset $end
$var reg 1 ! q $end
$upscope $end
$upscope $end
$upscope $end
$enddefinitions $end
$comment Show the parameter values. $end
$dumpall
$end
#0
$dumpvars
0&
0%
0$
1#
0"
0!
$end
#5
1"
#10
0"
0#
#15
1"
#20
0"
#25
1"
#30
0"
#35
1"
#40
0"
1%
1&
1$
#45
1!
1"
#50
0"
#55
0!
1"
#60
0"
#65
1!
1"
#70
0"
#75
0!
1"
#80
0"
0%
0&
0$
