rtl/combinational/encoder-mux/decoder_3to8.v
module decoder_3to8(
    input wire [2:0] in,
    input wire enable,
    output reg [7:0] out

);


always @(*) begin

    if(!enable)
    out=8'h00;
    else
    case (in)
        3'b000:out=8'b00000001;
        3'b001:out=8'b00000010; 
        3'b010:out=8'b00000100; 
        3'b011:out=8'b00001000; 
        3'b100:out=8'b00010000; 
        3'b101:out=8'b00100000; 
        3'b110:out=8'b01000000; 
        3'b111:out=8'b10000000; 

        default: out = 8'h00;
    endcase
    
end


endmodule

tb/tb_decoder_3to8.v


module tb_decoder_3to8;

reg [2:0] in;
reg enable;
wire [7:0] out;

decoder_3to8 dut
(
    .in(in),.enable(enable),.out(out)
);

integer pass_count, fail_count;
task check;
input [7:0] expected_out;
input [35:0] test_num;
begin
  #1;
  if (out===expected_out) begin
    $display("pass [test %0d] , in = %b , out =%0d",test_num,in,out);
    pass_count+=1;
  end
  else begin 
    $display("fail[test %0d],in=%b,out=%0d",test_num,in,out);
    fail_count+=1;
  end
end 


endtask

initial begin
    $dumpfile("tb_decoder_3to8.vcd");
    $dumpvars(0, tb_decoder_3to8);
end

initial begin
    pass_count=0;
    fail_count=0;

    enable=1'b1;

    in = 3'b000; check(8'b00000001,1);
    in = 3'b001; check(8'b00000010,2);
    in = 3'b010; check(8'b00000100,3);
    in = 3'b011; check(8'b00001000,4);
    in = 3'b100; check(8'b00010000,5);
    in = 3'b101; check(8'b00100000,6);
    in = 3'b110; check(8'b01000000,7);
    in = 3'b111; check(8'b10000000,8);
    
    enable=1'b0;

    in = 3'b000; check(8'b00000001,9);
    in = 3'b001; check(8'b00000010,10);
    in = 3'b010; check(8'b00000100,11);
    in = 3'b011; check(8'b00001000,12);
    in = 3'b100; check(8'b00010000,13);
    in = 3'b101; check(8'b00100000,14);
    in = 3'b110; check(8'b01000000,15);
    in = 3'b111; check(8'b10000000,16);

    $display("---------------------");
    $display("total %d passed , %d failed",pass_count,fail_count);
    if (fail_count == 0) begin
        $display("all test passed");
    end
    else
    $display("failure detected");
   
end

endmodule

tb_decoder_3to8.vcd
$date
	Wed Jun 17 11:16:04 2026
$end
$version
	Icarus Verilog
$end
$timescale
	1s
$end
$scope module tb_decoder_3to8 $end
$var wire 8 ! out [7:0] $end
$var reg 1 " enable $end
$var reg 3 # in [2:0] $end
$var integer 32 $ fail_count [31:0] $end
$var integer 32 % pass_count [31:0] $end
$scope module dut $end
$var wire 1 " enable $end
$var wire 3 & in [2:0] $end
$var reg 8 ' out [7:0] $end
$upscope $end
$scope task check $end
$var reg 8 ( expected_out [7:0] $end
$var reg 36 ) test_num [35:0] $end
$upscope $end
$upscope $end
$enddefinitions $end
$comment Show the parameter values. $end
$dumpall
$end
#0
$dumpvars
b1 )
b1 (
b1 '
b0 &
b0 %
b0 $
b0 #
1"
b1 !
$end
#1
b10 !
b10 '
b10 )
b10 (
b1 #
b1 &
b1 %
#2
b100 !
b100 '
b11 )
b100 (
b10 #
b10 &
b10 %
#3
b1000 !
b1000 '
b100 )
b1000 (
b11 #
b11 &
b11 %
#4
b10000 !
b10000 '
b101 )
b10000 (
b100 #
b100 &
b100 %
#5
b100000 !
b100000 '
b110 )
b100000 (
b101 #
b101 &
b101 %
#6
b1000000 !
b1000000 '
b111 )
b1000000 (
b110 #
b110 &
b110 %
#7
b10000000 !
b10000000 '
b1000 )
b10000000 (
b111 #
b111 &
b111 %
#8
b0 !
b0 '
b1001 )
b0 (
b0 #
b0 &
0"
b1000 %
#9
b1010 )
b1 #
b1 &
b1001 %
#10
b1011 )
b10 #
b10 &
b1010 %
#11
b1100 )
b11 #
b11 &
b1011 %
#12
b1101 )
b100 #
b100 &
b1100 %
#13
b1110 )
b101 #
b101 &
b1101 %
#14
b1111 )
b110 #
b110 &
b1110 %
#15
b10000 )
b111 #
b111 &
b1111 %
#16
b10000 %
