rtl/gates/priorty_encoder4to2.v
module priorty_encoder4to2(
    input wire  [3:0] in,
    input wire enable,
    output reg [1:0] out,
    output reg valid
);

always @(*) begin
    out = 2'b00;
    valid=1'b0;
    if (enable) begin
        if (in[3]) begin
            out=2'b11;
            valid=1'b1;
        end
        else if (in[2]) begin
            out=2'b10;
            valid=1'b1;
        end
        else if (in[1]) begin 
            out=2'b01;
            valid=1'b1;
            end
            else if (in[0]) begin 
                out=2'b00;
                valid=1'b1;
                end
    end
end

endmodule

tb/tb_priorty_encoder4to2.v
`timescale 1ns/1ps

module tb_priorty_encoder4to2;

reg [3:0] in;
wire [1:0]out;
wire valid;
reg enable;
priorty_encoder4to2 dut(
    .in(in),
    .out(out),
    .valid(valid),
    .enable(enable)
);

integer pass_count;
integer fail_count;
integer total_count;

task check;
    input [1:0] expected;
    input expected_valid;
    input integer test_num;
    begin
        #1;
        total_count = total_count + 1;

        if (out === expected && valid ===expected_valid) begin
            pass_count = pass_count + 1;
            $display("PASS [Test %0d] in=%b out = %0d valid = %b", test_num,in,out,valid);
        end
        else begin
            fail_count = fail_count + 1;
            $display("FAIL [Test %0d]", test_num);
        end
    end
endtask

initial begin
    $dumpfile("tb_priorty_encoder4to2.vcd");
    $dumpvars(0, tb_priorty_encoder4to2);
end

initial begin
    pass_count = 0;
    fail_count = 0;
    total_count = 0;

    // Test cases

    enable = 1'b1;

    in=4'b0000; check(2'b00,1'b0,1);
    in=4'b0001; check(2'b00,1'b1,2);
    in=4'b0010; check(2'b01,1'b1,3);
    in=4'b0100; check(2'b10,1'b1,4);
    in=4'b1000; check(2'b11,1'b1,5);
    in=4'b0011; check(2'b01,1'b1,6);
    in=4'b0111; check(2'b10,1'b1,7);
    in=4'b1001; check(2'b11,1'b1,8);
    in=4'b1111; check(2'b11,1'b1,9);

    enable = 1'b0;
    in=4'b0000; check(2'b00,1'b0,10);
    in=4'b0001; check(2'b00,1'b0,11);
    in=4'b0010; check(2'b00,1'b0,12);
    in=4'b0100; check(2'b00,1'b0,13);
    in=4'b1000; check(2'b00,1'b0,14);
    in=4'b0011; check(2'b00,1'b0,15);
    in=4'b0111; check(2'b00,1'b0,16);
    in=4'b1001; check(2'b00,1'b0,17);
    in=4'b1111; check(2'b00,1'b0,18);






    $display("----------------------");
    $display("Total  : %0d", total_count);
    $display("Passed : %0d", pass_count);
    $display("Failed : %0d", fail_count);

    $finish;
end

endmodule

tb_priorty_encoder4to2.vcd
$date
	Fri Jun 19 12:05:52 2026
$end
$version
	Icarus Verilog
$end
$timescale
	1ps
$end
$scope module tb_priorty_encoder4to2 $end
$var wire 1 ! valid $end
$var wire 2 " out [1:0] $end
$var reg 1 # enable $end
$var reg 4 $ in [3:0] $end
$var integer 32 % fail_count [31:0] $end
$var integer 32 & pass_count [31:0] $end
$var integer 32 ' total_count [31:0] $end
$scope module dut $end
$var wire 1 # enable $end
$var wire 4 ( in [3:0] $end
$var reg 2 ) out [1:0] $end
$var reg 1 ! valid $end
$upscope $end
$scope task check $end
$var reg 2 * expected [1:0] $end
$var reg 1 + expected_valid $end
$var integer 32 , test_num [31:0] $end
$upscope $end
$upscope $end
$enddefinitions $end
$comment Show the parameter values. $end
$dumpall
$end
#0
$dumpvars
b1 ,
0+
b0 *
b0 )
b0 (
b0 '
b0 &
b0 %
b0 $
1#
b0 "
0!
$end
#1000
1!
b10 ,
1+
b1 $
b1 (
b1 &
b1 '
#2000
b1 "
b1 )
1!
b11 ,
b1 *
b10 $
b10 (
b10 &
b10 '
#3000
1!
b10 "
b10 )
b100 ,
b10 *
b100 $
b100 (
b11 &
b11 '
#4000
1!
b11 "
b11 )
b101 ,
b11 *
b1000 $
b1000 (
b100 &
b100 '
#5000
1!
b1 "
b1 )
b110 ,
b1 *
b11 $
b11 (
b101 &
b101 '
#6000
1!
b10 "
b10 )
b111 ,
b10 *
b111 $
b111 (
b110 &
b110 '
#7000
1!
b11 "
b11 )
b1000 ,
b11 *
b1001 $
b1001 (
b111 &
b111 '
#8000
1!
b11 "
b11 )
b1001 ,
b1111 $
b1111 (
b1000 &
b1000 '
#9000
0!
b0 "
b0 )
b1010 ,
0+
b0 *
b0 $
b0 (
0#
b1001 &
b1001 '
#10000
b1011 ,
b1 $
b1 (
b1010 &
b1010 '
#11000
b1100 ,
b10 $
b10 (
b1011 &
b1011 '
#12000
b1101 ,
b100 $
b100 (
b1100 &
b1100 '
#13000
b1110 ,
b1000 $
b1000 (
b1101 &
b1101 '
#14000
b1111 ,
b11 $
b11 (
b1110 &
b1110 '
#15000
b10000 ,
b111 $
b111 (
b1111 &
b1111 '
#16000
b10001 ,
b1001 $
b1001 (
b10000 &
b10000 '
#17000
b10010 ,
b1111 $
b1111 (
b10001 &
b10001 '
#18000
b10010 &
b10010 '
