rtl/sequntial/fsm/vending_machine.v
//vending machine desgin.

module vending_machine(
    input wire clk, rst,
    input wire [1:0] coin,
    output reg [5:0] change,
    output reg item
);

localparam NO_COIN  = 2'b00;
localparam FIVE     = 2'b01;
localparam TEN      = 2'b10;
localparam FIFTEEN  = 2'b11;

localparam S_IDLE  = 1'b0;
localparam S_ITEM  = 1'b1;

reg current_state, next_state;
reg [5:0] amount, next_amount;
reg [5:0] final_amount;

always @(posedge clk or posedge rst) begin
    if (rst) begin
        current_state <= S_IDLE;
        amount <= 6'd0;
        final_amount <= 6'd0;
    end else begin
        current_state <= next_state;
        amount <= next_amount;

        if (next_state == S_ITEM)
            final_amount <= next_amount;
    end
end

always @(*) begin
    next_state  = current_state;
    next_amount = amount;

    case (current_state)

        S_IDLE: begin
            case (coin)
                NO_COIN:   next_amount = amount;
                FIVE:      next_amount = amount + 6'd5;
                TEN:       next_amount = amount + 6'd10;
                FIFTEEN:   next_amount = amount + 6'd15;
            endcase

            if (next_amount >= 6'd15 && coin == NO_COIN)
                next_state = S_ITEM;
        end

        S_ITEM: begin
            next_state  = S_IDLE;
            next_amount = 6'd0;
        end

    endcase
end

always @(*) begin
    item   = 0;
    change = 0;

    case (current_state)

        S_IDLE: begin
            item = 0;
            change = 0;
        end

        S_ITEM: begin
            item = 1;
            change = final_amount - 6'd15;
        end

    endcase
end

endmodule

tb/tb_vending_machine.v
// writing a testbench for vending machine desgin.



module tb_vending_machine;
reg clk;
reg rst;
reg [1:0] coin;
wire [5:0] change;
wire item;

 
vending_machine dut (
    .rst(rst),
    .clk(clk),
    .coin(coin), .change(change),
    .item(item)
);

localparam no_coin = 2'b00 ;
localparam five = 2'b01 ;
localparam ten = 2'b10 ;
localparam fifteen = 2'b11 ;

initial begin
    clk = 0;
    forever #5 clk = ~clk;
end

initial begin
    $dumpfile("tb_vending_mchine.vcd");
    $dumpvars(0, tb_vending_machine);
    $display("time | coin | amount | item | change |");
    $display("======================================");
end

initial begin
   rst = 1; coin = no_coin; #12;
   rst = 0; #10;

   //test - 1 exact change
   coin = fifteen; #10;
   coin = no_coin; #12;

   //test-2 multiple coins
   coin=no_coin; #10;
   coin = ten; #10;
   coin = five; #10;
   coin = no_coin; #12;

   //test -3
   coin = five; #10;
   coin = ten; #10;
   coin = five; #10;
   coin = no_coin; #12;

   // test-4
   coin=no_coin; #10;
   coin = five; #10;
   coin = five; #10;
   coin = five; #10;
   coin = five; #10;
   coin = five; #10;
   coin = no_coin; #12;

   #20;  
   $finish;



end

always @(posedge clk) begin
    $display("%4t | %s | %2d$ | %b | %2d$",
    $time,
    (coin == no_coin) ? "noone":
    (coin == five)? "5$":
    (coin == ten) ? "10$":
    (coin == fifteen) ? "15$": "????",
    dut.amount, item , change
    );
end

endmodule

tb_vending_mchine.vcd
$date
	Tue Jun  2 09:52:48 2026
$end
$version
	Icarus Verilog
$end
$timescale
	1s
$end
$scope module tb_vending_machine $end
$var wire 1 ! item $end
$var wire 6 " change [5:0] $end
$var parameter 2 # fifteen $end
$var parameter 2 $ five $end
$var parameter 2 % no_coin $end
$var parameter 2 & ten $end
$var reg 1 ' clk $end
$var reg 2 ( coin [1:0] $end
$var reg 1 ) rst $end
$scope module dut $end
$var wire 1 ' clk $end
$var wire 2 * coin [1:0] $end
$var wire 1 ) rst $end
$var parameter 2 + FIFTEEN $end
$var parameter 2 , FIVE $end
$var parameter 2 - NO_COIN $end
$var parameter 1 . S_IDLE $end
$var parameter 1 / S_ITEM $end
$var parameter 2 0 TEN $end
$var reg 6 1 amount [5:0] $end
$var reg 6 2 change [5:0] $end
$var reg 1 3 current_state $end
$var reg 6 4 final_amount [5:0] $end
$var reg 1 ! item $end
$var reg 6 5 next_amount [5:0] $end
$var reg 1 6 next_state $end
$upscope $end
$upscope $end
$enddefinitions $end
$comment Show the parameter values. $end
$dumpall
b10 0
1/
0.
b0 -
b1 ,
b11 +
b10 &
b0 %
b1 $
b11 #
$end
#0
$dumpvars
06
b0 5
b0 4
03
b0 2
b0 1
b0 *
1)
b0 (
0'
b0 "
0!
$end
#5
1'
#10
0'
#12
0)
#15
1'
#20
0'
#22
b1111 5
b11 (
b11 *
#25
b11110 5
b1111 1
1'
#30
0'
#32
16
b1111 5
b0 (
b0 *
#35
1!
b0 5
06
b1111 4
13
1'
#40
0'
#45
0!
b0 1
03
1'
#50
0'
#54
b1010 5
b10 (
b10 *
#55
b10100 5
b1010 1
1'
#60
0'
#64
b1111 5
b1 (
b1 *
#65
b10100 5
b1111 1
1'
#70
0'
#74
16
b1111 5
b0 (
b0 *
#75
1!
b0 5
06
13
1'
#80
0'
#85
0!
b0 1
03
1'
#86
b101 5
b1 (
b1 *
#90
0'
#95
b1010 5
b101 1
1'
#96
b1111 5
b10 (
b10 *
#100
0'
#105
b11001 5
b1111 1
1'
#106
b10100 5
b1 (
b1 *
#110
0'
#115
b11001 5
b10100 1
1'
#116
16
b10100 5
b0 (
b0 *
#120
0'
#125
b101 "
b101 2
1!
b0 5
06
b10100 4
13
1'
#130
0'
#135
b0 "
b0 2
0!
b0 1
03
1'
#138
b101 5
b1 (
b1 *
#140
0'
#145
b1010 5
b101 1
1'
#150
0'
#155
b1111 5
b1010 1
1'
#160
0'
#165
b10100 5
b1111 1
1'
#170
0'
#175
b11001 5
b10100 1
1'
#180
0'
#185
b11110 5
b11001 1
1'
#188
16
b11001 5
b0 (
b0 *
#190
0'
#195
b1010 "
b1010 2
1!
b0 5
06
b11001 4
13
1'
#200
0'
#205
b0 "
b0 2
0!
b0 1
03
1'
