rtl/flip_flops/traffic_light.v
// a traffic light controller with moore fsm

module traffic_light(
    input wire clk , rst, timer , 
    output reg red , green , yellow

);

localparam RED = 2'b00;
localparam GREEN = 2'b01;
localparam YELLOW = 2'b10;

reg [1:0] current_state , next_state;

always @(posedge clk or posedge rst) begin
    if (rst) begin
        current_state <= RED;

    end
    else
    current_state<=next_state;

end

always @(*) begin
    case (current_state)
        RED:next_state = (timer) ? GREEN : RED;
        GREEN: next_state = (timer) ? YELLOW: GREEN;
        YELLOW: next_state = (timer) ? RED : YELLOW;
        default: next_state = RED;
    endcase
end

always @(*) begin
    red = 0 ; yellow = 0 ; green = 0;

    case(current_state) 
    RED: red=1;
    YELLOW: yellow=1;
    GREEN: green=1;

    endcase
end


endmodule

tb/tb_traffic_light.v
module tb_traffic_light;

reg clk , rst , timer;
wire red , green , yellow;

traffic_light dut(
    .clk(clk), .rst(rst) , .timer(timer),
    .red(red), .green(green), .yellow(yellow)
);

initial begin
    clk = 0;
    forever #5 clk = ~clk;
end

initial begin 
    $dumpfile("traffic_light.vcd");
    $dumpvars(0,tb_traffic_light);
    $display("time | rst | timer |  R | Y | G | state ");
    $display("========================================");

    rst = 1; timer =0; #10;
    rst = 0 ; #10;
    timer = 1; #10;
    timer = 0; #10;
    timer = 1; #10;
    timer = 0; #10;
    timer = 1; #10;
    timer = 0; #10;
    timer = 1; #10;
    timer = 0; #10;
    timer = 1; #10;
    timer = 0; #10;
    timer = 1; #10;
    timer = 0; #10;

    $finish;

end

always @(posedge clk) begin
    $display("%4t | %b | %b | %b | %b | %b | %s | ",
    $time , rst , timer , red,yellow,green,
    (dut.current_state == 2'b00) ? "RED":
    (dut.current_state == 2'b01) ? "GREEN":
    (dut.current_state == 2'b10) ? "YELLOW":"unkown");
    
end


endmodule

traffic_light.vcd
$date
	Wed Apr  8 11:50:29 2026
$end
$version
	Icarus Verilog
$end
$timescale
	1s
$end
$scope module tb_traffic_light $end
$var wire 1 ! yellow $end
$var wire 1 " red $end
$var wire 1 # green $end
$var reg 1 $ clk $end
$var reg 1 % rst $end
$var reg 1 & timer $end
$scope module dut $end
$var wire 1 $ clk $end
$var wire 1 % rst $end
$var wire 1 & timer $end
$var parameter 2 ' GREEN $end
$var parameter 2 ( RED $end
$var parameter 2 ) YELLOW $end
$var reg 2 * current_state [1:0] $end
$var reg 1 # green $end
$var reg 2 + next_state [1:0] $end
$var reg 1 " red $end
$var reg 1 ! yellow $end
$upscope $end
$upscope $end
$enddefinitions $end
$comment Show the parameter values. $end
$dumpall
b10 )
b0 (
b1 '
$end
#0
$dumpvars
b0 +
b0 *
0&
1%
0$
0#
1"
0!
$end
#5
1$
#10
0$
0%
#15
1$
#20
b1 +
0$
1&
#25
1#
0"
b10 +
b1 *
1$
#30
b1 +
0$
0&
#35
1$
#40
b10 +
0$
1&
#45
1!
0#
b0 +
b10 *
1$
#50
b10 +
0$
0&
#55
1$
#60
b0 +
0$
1&
#65
1"
0!
b1 +
b0 *
1$
#70
b0 +
0$
0&
#75
1$
#80
b1 +
0$
1&
#85
1#
0"
b10 +
b1 *
1$
#90
b1 +
0$
0&
#95
1$
#100
b10 +
0$
1&
#105
1!
0#
b0 +
b10 *
1$
#110
b10 +
0$
0&
#115
1$
#120
b0 +
0$
1&
#125
1"
0!
b1 +
b0 *
1$
#130
b0 +
0$
0&
