rtl/flip_flops/universal_register.v
module universal_register(
    input wire clk,reset,si,
    input wire [1:0] mode,
    input wire [7:0] pi,
    output reg [7:0] po,
    output wire so_right,
    output wire so_left
);

localparam hold = 2'b00;
localparam shift_right = 2'b01;
localparam shift_left = 2'b10;
localparam load = 2'b11;

always @(posedge clk or posedge reset) begin
    if(reset)
    po <= 8'b0;
    else
    case (mode)
        hold: po <= po;
        shift_left: po <= {po[6:0] , si};
        shift_right: po <=  {si, po[7:1]};
        load: po <= pi;        
        default: po <= po;
    endcase
    
end

assign so_left = po[7];
assign so_right = po[0];

endmodule

tb/tb_universal_register.v
module tb_universal_register;

reg clk,reset,si;
reg [1:0] mode;
reg [7:0] pi;
wire [7:0] po;
wire so_left, so_right;

localparam hold = 2'b00;
localparam shift_right = 2'b01;
localparam shift_left = 2'b10;
localparam load = 2'b11;

universal_register dut(
    .clk(clk),
    .reset(reset),
    .mode(mode),
    .si(si),
    .pi(pi),
    .po(po),
    .so_right(so_right),
    .so_left(so_left)
);

initial begin
    clk = 0;
    forever #5 clk = ~clk;
end

initial begin
    $dumpfile("universal_register.vcd");
    $dumpvars(0,tb_universal_register);
    $display("Time | mode | si | pi       | po       | so_L | so_R");
    $display("----------------------------------------------------");
    $monitor("%4t | %b   | %b  | %b | %b | %b    | %b",
    $time,mode,si,pi,po,so_left,so_right);

    //intilize
    reset=1; mode = hold; si=0; pi=8'b0; #10;

    reset=0;
    #10;

    //test-1 parllel load

    pi = 8'b10110011;
    mode = load;
    #10;

    //test-2 hold

    mode = hold;
    pi = 8'b11111111;
    #20;

    //test-3 shift right (si=1 then si = 0)

    mode =  shift_right;
    si =1; #10;
    si=0; #10;
    si=1; #10;

    //test-4 reload and shift left
    mode = load;
    pi = 8'b10110011;
    #10;
    mode = shift_left;
    si=1; #10;
    si=0; #10;
    si=1; #10;

    //test-5 shift right multiple times

    mode = load;

    pi = 8'b10110011;

    #10;

    mode = shift_right;
    si = 0;
    repeat(8) #10;

    $finish;




end


endmodule

universal_register.vcd
$date
	Mon Feb 23 19:59:08 2026
$end
$version
	Icarus Verilog
$end
$timescale
	1s
$end
$scope module tb_universal_register $end
$var wire 1 ! so_right $end
$var wire 1 " so_left $end
$var wire 8 # po [7:0] $end
$var parameter 2 $ hold $end
$var parameter 2 % load $end
$var parameter 2 & shift_left $end
$var parameter 2 ' shift_right $end
$var reg 1 ( clk $end
$var reg 2 ) mode [1:0] $end
$var reg 8 * pi [7:0] $end
$var reg 1 + reset $end
$var reg 1 , si $end
$scope module dut $end
$var wire 1 ( clk $end
$var wire 2 - mode [1:0] $end
$var wire 8 . pi [7:0] $end
$var wire 1 + reset $end
$var wire 1 , si $end
$var wire 1 ! so_right $end
$var wire 1 " so_left $end
$var parameter 2 / hold $end
$var parameter 2 0 load $end
$var parameter 2 1 shift_left $end
$var parameter 2 2 shift_right $end
$var reg 8 3 po [7:0] $end
$upscope $end
$upscope $end
$enddefinitions $end
$comment Show the parameter values. $end
$dumpall
b1 2
b10 1
b11 0
b0 /
b1 '
b10 &
b11 %
b0 $
$end
#0
$dumpvars
b0 3
b0 .
b0 -
0,
1+
b0 *
b0 )
0(
b0 #
0"
0!
$end
#5
1(
#10
0(
0+
#15
1(
#20
0(
b11 )
b11 -
b10110011 *
b10110011 .
#25
1"
1!
b10110011 #
b10110011 3
1(
#30
0(
b11111111 *
b11111111 .
b0 )
b0 -
#35
1(
#40
0(
#45
1(
#50
0(
1,
b1 )
b1 -
#55
b11011001 #
b11011001 3
1(
#60
0(
0,
#65
0"
0!
b1101100 #
b1101100 3
1(
#70
0(
1,
#75
1"
b10110110 #
b10110110 3
1(
#80
0(
b10110011 *
b10110011 .
b11 )
b11 -
#85
1!
b10110011 #
b10110011 3
1(
#90
0(
b10 )
b10 -
#95
0"
b1100111 #
b1100111 3
1(
#100
0(
0,
#105
1"
0!
b11001110 #
b11001110 3
1(
#110
0(
1,
#115
1!
b10011101 #
b10011101 3
1(
#120
0(
b11 )
b11 -
#125
b10110011 #
b10110011 3
1(
#130
0(
0,
b1 )
b1 -
#135
0"
b1011001 #
b1011001 3
1(
#140
0(
#145
0!
b101100 #
b101100 3
1(
#150
0(
#155
b10110 #
b10110 3
1(
#160
0(
#165
1!
b1011 #
b1011 3
1(
#170
0(
#175
b101 #
b101 3
1(
#180
0(
#185
0!
b10 #
b10 3
1(
#190
0(
#195
1!
b1 #
b1 3
1(
#200
0(
#205
0!
b0 #
b0 3
1(
