tb_mux.v
module mux(
    input wire a,
    input wire b,
    input wire sel,
    output reg y
);

    always @(*) begin
        if (sel)
            y = b;
        else
            y = a;
    end

endmodule


module tb_mux;
    reg a, b, sel;
    wire y;

    mux dut(
        .a(a),
        .b(b),
        .sel(sel),
        .y(y)
    );
    
    initial begin
        $dumpfile("mux.vcd");
        $dumpvars(0, tb_mux);
        
        $display("test started");
        $display("time | a | b | sel | y");
        $display("______________________|");
        
        a = 0; b = 0; sel = 0; #10;
        $display("|%4t | %b | %b | %b   | %b|", $time, a, b, sel, y);
        
        a = 0; b = 0; sel = 1; #10;
        $display("|%4t | %b | %b | %b   | %b|", $time, a, b, sel, y);
        
        a = 0; b = 1; sel = 0; #10;
        $display("|%4t | %b | %b | %b   | %b|", $time, a, b, sel, y);
        
        a = 0; b = 1; sel = 1; #10;
        $display("|%4t | %b | %b | %b   | %b|", $time, a, b, sel, y);
        
        a = 1; b = 0; sel = 0; #10;
        $display("|%4t | %b | %b | %b   | %b|", $time, a, b, sel, y);
        
        a = 1; b = 0; sel = 1; #10;
        $display("|%4t | %b | %b | %b   | %b|", $time, a, b, sel, y);
        
        a = 1; b = 1; sel = 0; #10;
        $display("|%4t | %b | %b | %b   | %b|", $time, a, b, sel, y);
        
        a = 1; b = 1; sel = 1; #10;
        $display("|%4t | %b | %b | %b   | %b|", $time, a, b, sel, y);
        
        $display("test completed");
        $finish;
    end

endmodule

sim/mux.vcd
$date
	Sat Dec 20 21:07:36 2025
$end
$version
	Icarus Verilog
$end
$timescale
	1s
$end
$scope module tb_mux $end
$var wire 1 ! y $end
$var reg 1 " a $end
$var reg 1 # b $end
$var reg 1 $ sel $end
$scope module dut $end
$var wire 1 " a $end
$var wire 1 # b $end
$var wire 1 $ sel $end
$var reg 1 ! y $end
$upscope $end
$upscope $end
$enddefinitions $end
$comment Show the parameter values. $end
$dumpall
$end
#0
$dumpvars
0$
0#
0"
0!
$end
#10
1$
#20
0$
1#
#30
1!
1$
#40
0$
0#
1"
#50
0!
1$
#60
1!
0$
1#
#70
1$
