rtl/flip_flops/12_bit_counter.v
module div12_bit_counter(
    input wire clk , rst , en , load,
    input wire [3:0] data,
    output reg [3:0] count
);

always @(posedge clk or posedge rst) begin

    if(rst)
    count <= 4'd0;
    else if (load)
    count <= data;
    else if (en) begin
        if(count == 4'd11 )
        count <= 4'd0;
        else
        count <= count + 1'd1;
    end
    
end

endmodule

tb/tb_12_bit_counter.v
module tb_12_bit_counter;

reg clk, rst , en , load;
reg [3:0] data;
wire [3:0] count;

div12_bit_counter dut(
    .clk(clk),
    .rst(rst),
    .en(en),
    .load(load),
    .data(data),
    .count(count)
);

initial begin
    clk = 0;
    forever #5 clk = ~clk;

end
initial begin
    $dumpfile("12_bit_counter.vcd");
    $dumpvars(0,tb_12_bit_counter);
    $display("time | rst | en | load | data | count | ");
    $display("---------------------------------------");
    $monitor("%4t | %3d | %3d | %3d | %3d | %3d |",$time,rst,en,load,data,count);

    //intilize
    
    rst =1 ; en = 1 ; load = 0 ; data =4'd8;
    #10;
    
    rst=0;
    #10;
    
    //count up
    
    en = 1 ; load = 0; data = 4'd8;
    #50;
    
    //disable enable
    
    en = 0 ; load = 0; data = 4'd8;
    #50;
    
    //load the value
    
    en = 0; load = 1; data = 4'd8;
    #50;
    
    //enable again
    
    en = 1; load = 0; data = 4'd8;

    #95;
    
    //async reset 
    rst = 1; load = 1 ; en = 1; data = 4'd5;
    #20;
    
    $finish;

end

endmodule

vcd/12_bit_counter.vcd
$date
	Fri Mar 27 11:32:22 2026
$end
$version
	Icarus Verilog
$end
$timescale
	1s
$end
$scope module tb_12_bit_counter $end
$var wire 4 ! count [3:0] $end
$var reg 1 " clk $end
$var reg 4 # data [3:0] $end
$var reg 1 $ en $end
$var reg 1 % load $end
$var reg 1 & rst $end
$scope module dut $end
$var wire 1 " clk $end
$var wire 4 ' data [3:0] $end
$var wire 1 $ en $end
$var wire 1 % load $end
$var wire 1 & rst $end
$var reg 4 ( count [3:0] $end
$upscope $end
$upscope $end
$enddefinitions $end
$comment Show the parameter values. $end
$dumpall
$end
#0
$dumpvars
b0 (
b1000 '
1&
0%
1$
b1000 #
0"
b0 !
$end
#5
1"
#10
0"
0&
#15
b1 !
b1 (
1"
#20
0"
#25
b10 !
b10 (
1"
#30
0"
#35
b11 !
b11 (
1"
#40
0"
#45
b100 !
b100 (
1"
#50
0"
#55
b101 !
b101 (
1"
#60
0"
#65
b110 !
b110 (
1"
#70
0"
0$
#75
1"
#80
0"
#85
1"
#90
0"
#95
1"
#100
0"
#105
1"
#110
0"
#115
1"
#120
0"
1%
#125
b1000 !
b1000 (
1"
#130
0"
#135
1"
#140
0"
#145
1"
#150
0"
#155
1"
#160
0"
#165
1"
#170
0"
0%
1$
#175
b1001 !
b1001 (
1"
#180
0"
#185
b1010 !
b1010 (
1"
#190
0"
#195
b1011 !
b1011 (
1"
#200
0"
#205
b0 !
b0 (
1"
#210
0"
#215
b1 !
b1 (
1"
#220
0"
#225
b10 !
b10 (
1"
#230
0"
#235
b11 !
b11 (
1"
#240
0"
#245
b100 !
b100 (
1"
#250
0"
#255
b101 !
b101 (
1"
#260
0"
#265
b0 !
b0 (
1"
b101 #
b101 '
1%
1&
