rtl/flip_flops/paramatized_n_bit_register.v
module reg_param #(
    parameter n = 8     // No semicolon here!
)(
    input wire clk, reset, en,
    input wire [n-1:0] d,
    output reg [n-1:0] q
);

    always @(posedge clk or posedge reset) begin
        if (reset)
            q <= {n{1'b0}};
        else if (en)
            q <= d;
        else
            q <= q;
    end

endmodule

tb/tb_n_bit_register.v
module tb_n_bit_register;

    reg clk, reset, en;

    reg  [3:0]  d_4;
    reg  [7:0]  d_8;
    reg  [15:0] d_16;

    wire [3:0]  q_4;
    wire [7:0]  q_8;
    wire [15:0] q_16;

    // Instantiate 4-bit register
    reg_param #(.n(4)) reg_4bit (
        .clk(clk),
        .reset(reset),
        .en(en),
        .d(d_4),        // Connect d_4 to module port 'd'
        .q(q_4)         // Connect q_4 to module port 'q'
    );

    // Instantiate 8-bit register
    reg_param #(.n(8)) reg_8bit (
        .clk(clk),
        .reset(reset),
        .en(en),
        .d(d_8),        // Connect d_8 to module port 'd'
        .q(q_8)
    );

    // Instantiate 16-bit register
    reg_param #(.n(16)) reg_16bit (
        .clk(clk),
        .reset(reset),
        .en(en),
        .d(d_16),       // Connect d_16 to module port 'd'
        .q(q_16)
    );

    // Clock generator
    initial begin
        clk = 0;
        forever #5 clk = ~clk;
    end

    // Test stimulus
    initial begin
        $dumpfile("parameterized_n_bit_register.vcd");
        $dumpvars(0, tb_n_bit_register);

        $display("Time | rst | en | d_4  | d_8  | d_16 | q_4  | q_8  | q_16");
        $display("--------------------------------------------------------------");
        $monitor("%4t |  %b  | %b | %h   | %h   | %h   | %h   | %h   | %h", 
                 $time, reset, en, d_4, d_8, d_16, q_4, q_8, q_16);

        // Initialize
        reset = 1; en = 0;
        d_4 = 4'h0;
        d_8 = 8'h00;
        d_16 = 16'h0000;
        #10;

        // Release reset
        reset = 0;
        #10;

        // Test 1: Load data with enable=1
      
        en = 1;
        d_4  = 4'hA;        // 4-bit: 1010
        d_8  = 8'h5C;       // 8-bit: 0101_1100
        d_16 = 16'hBEEF;    // 16-bit: 1011_1110_1110_1111
        #10;

        // Test 2: Change data (should load immediately)
        d_4  = 4'hF;
        d_8  = 8'hFF;
        d_16 = 16'hAAAA;
        #10;

        // Test 3: Hold with enable=0
        
        en = 0;
        d_4  = 4'h0;        // Data changes, but registers should HOLD
        d_8  = 8'h00;
        d_16 = 16'h0000;
        #20;                // Hold for 2 clock cycles

        // Test 4: Re-enable and load
       
        en = 1;
        d_4  = 4'h7;
        d_8  = 8'h42;
        d_16 = 16'h1234;
        #10;

        // Test 5: Test maximum values for each width
        
        d_4  = 4'hF;        // Max for 4-bit: 1111
        d_8  = 8'hFF;       // Max for 8-bit: 1111_1111
        d_16 = 16'hFFFF;    // Max for 16-bit
        #10;

        // Test 6: Async reset during operation
       
        d_4  = 4'hA;
        d_8  = 8'hCC;
        d_16 = 16'h9999;
        #5;                 // Mid-cycle
        reset = 1;
        #10;
        reset = 0;
        #10;

        $finish;
    end

endmodule

vcd/parameterized_n_bit_register.vcd
$date
	Tue Feb 17 08:31:30 2026
$end
$version
	Icarus Verilog
$end
$timescale
	1s
$end
$scope module tb_n_bit_register $end
$var wire 8 ! q_8 [7:0] $end
$var wire 4 " q_4 [3:0] $end
$var wire 16 # q_16 [15:0] $end
$var reg 1 $ clk $end
$var reg 16 % d_16 [15:0] $end
$var reg 4 & d_4 [3:0] $end
$var reg 8 ' d_8 [7:0] $end
$var reg 1 ( en $end
$var reg 1 ) reset $end
$scope module reg_16bit $end
$var wire 1 $ clk $end
$var wire 16 * d [15:0] $end
$var wire 1 ( en $end
$var wire 1 ) reset $end
$var parameter 32 + n $end
$var reg 16 , q [15:0] $end
$upscope $end
$scope module reg_4bit $end
$var wire 1 $ clk $end
$var wire 4 - d [3:0] $end
$var wire 1 ( en $end
$var wire 1 ) reset $end
$var parameter 32 . n $end
$var reg 4 / q [3:0] $end
$upscope $end
$scope module reg_8bit $end
$var wire 1 $ clk $end
$var wire 8 0 d [7:0] $end
$var wire 1 ( en $end
$var wire 1 ) reset $end
$var parameter 32 1 n $end
$var reg 8 2 q [7:0] $end
$upscope $end
$upscope $end
$enddefinitions $end
$comment Show the parameter values. $end
$dumpall
b1000 1
b100 .
b10000 +
$end
#0
$dumpvars
b0 2
b0 0
b0 /
b0 -
b0 ,
b0 *
1)
0(
b0 '
b0 &
b0 %
0$
b0 #
b0 "
b0 !
$end
#5
1$
#10
0$
0)
#15
1$
#20
0$
b1011111011101111 %
b1011111011101111 *
b1011100 '
b1011100 0
b1010 &
b1010 -
1(
#25
b1011111011101111 #
b1011111011101111 ,
b1011100 !
b1011100 2
b1010 "
b1010 /
1$
#30
0$
b1010101010101010 %
b1010101010101010 *
b11111111 '
b11111111 0
b1111 &
b1111 -
#35
b1111 "
b1111 /
b11111111 !
b11111111 2
b1010101010101010 #
b1010101010101010 ,
1$
#40
0$
b0 %
b0 *
b0 '
b0 0
b0 &
b0 -
0(
#45
1$
#50
0$
#55
1$
#60
0$
b1001000110100 %
b1001000110100 *
b1000010 '
b1000010 0
b111 &
b111 -
1(
#65
b1001000110100 #
b1001000110100 ,
b1000010 !
b1000010 2
b111 "
b111 /
1$
#70
0$
b1111111111111111 %
b1111111111111111 *
b11111111 '
b11111111 0
b1111 &
b1111 -
#75
b1111 "
b1111 /
b11111111 !
b11111111 2
b1111111111111111 #
b1111111111111111 ,
1$
#80
0$
b1001100110011001 %
b1001100110011001 *
b11001100 '
b11001100 0
b1010 &
b1010 -
#85
b0 #
b0 ,
b0 !
b0 2
b0 "
b0 /
1$
1)
#90
0$
#95
b1010 "
b1010 /
b11001100 !
b11001100 2
b1001100110011001 #
b1001100110011001 ,
1$
0)
