rtl/flip_flops/piso.v
module piso(
    input wire clk,reset,load,
    input wire [7:0] pi,
    output wire so
);

reg [7:0] shift_reg;

always @(posedge clk or posedge reset) begin 
    if(reset)
    shift_reg <= 8'b0;
    else if (load)
    shift_reg <= pi;
    else
    shift_reg <= {shift_reg[6:0],1'b0};
end

assign so = shift_reg[7];

endmodule

tb/register/tb_piso.v
module tb_piso;
    reg clk,reset,load;
    reg [7:0] pi;
    wire so;
    


piso dut(
.clk(clk),
.reset(reset),
.load(load),
.pi(pi),
.so(so)
);

initial begin
    clk = 0;
    forever #5 clk = ~clk;
end

initial begin 
    $dumpfile("piso.vcd");
    $dumpvars(0,tb_piso);
    $display("Time | rst | load | pi       | so | shift_reg");
    $display("---------------------------------------------");
    $monitor("%4t |  %b  |  %b   | %b | %b  | %b", 
                 $time, reset, load, pi, so, dut.shift_reg);
    
    //reset 

    reset = 1;
    load = 0; #10;
    

    //realse reset
    reset = 0; #10;

    //load pi
    pi = 8'b10110011;
    #10;
    //load values
    load =1; #10;


    load =0; #80;
    $finish;
end


endmodule

vcd/piso.vcd
$date
	Sun Feb 22 13:11:50 2026
$end
$version
	Icarus Verilog
$end
$timescale
	1s
$end
$scope module tb_piso $end
$var wire 1 ! so $end
$var reg 1 " clk $end
$var reg 1 # load $end
$var reg 8 $ pi [7:0] $end
$var reg 1 % reset $end
$scope module dut $end
$var wire 1 " clk $end
$var wire 1 # load $end
$var wire 8 & pi [7:0] $end
$var wire 1 % reset $end
$var wire 1 ! so $end
$var reg 8 ' shift_reg [7:0] $end
$upscope $end
$upscope $end
$enddefinitions $end
$comment Show the parameter values. $end
$dumpall
$end
#0
$dumpvars
b0 '
bx &
1%
bx $
0#
0"
0!
$end
#5
1"
#10
0"
0%
#15
1"
#20
0"
b10110011 $
b10110011 &
#25
1"
#30
0"
1#
#35
1!
b10110011 '
1"
#40
0"
0#
#45
0!
b1100110 '
1"
#50
0"
#55
1!
b11001100 '
1"
#60
0"
#65
b10011000 '
1"
#70
0"
#75
0!
b110000 '
1"
#80
0"
#85
b1100000 '
1"
#90
0"
#95
1!
b11000000 '
1"
#100
0"
#105
b10000000 '
1"
#110
0"
#115
0!
b0 '
1"
