rtl/sequntial/fsm/squence_Detector.v
// a squence detector which detects the patter 101 and use melay transition 
//and overlaping patter recognistion

module squence_detector(
    input wire clk , rst,
    input wire in,
    output reg detected
);

localparam s0 = 2'b00;
localparam s1 = 2'b01;
localparam s10 = 2'b10;

reg [1:0] current_state , next_state;

always @(posedge clk or posedge rst) begin
    if(rst)
    current_state<=s0;
    else
    current_state<=next_state;

end

always @(*) begin
    case (current_state)
       s0 : begin
         if (in) begin
            next_state = s1;
         end
         else
         next_state = s0;
       end 
       s1: begin
         if (in) begin
            next_state = s1;
         end
         else
         next_state = s10;
       end
       s10: begin
         if (in) begin
            next_state = s1;
         end
         else
         next_state = s0;
       end
        default: next_state = s0;
    endcase
end

always @(*) begin
    if (current_state==s10 && in == 1) begin
        detected = 1;
    end
    else
    detected=0;
end
endmodule

tb/tb_squence_Detector.v
//testbench for the desgin squence detector to detect 101 
module tb_squence_detector;

reg clk , rst , in;
wire detected;

squence_detector dut(
    .clk(clk) , .rst(rst) , .in(in),
    .detected(detected)
);

initial begin
    clk=0;
    forever #5 clk=~clk;
end

initial begin
    $dumpfile("squence_detector.vcd");
    $dumpvars(0 , tb_squence_detector);
    $display("time | rst | in | detected | state | patter progerres");
    $display("======================================================");

    rst=1; in=0; #10;
    rst=0; #10;
    in =0; #10;
    in=1; #10;
    in =0; #10;
    in=1; #10;
    in =0; #10;
    in=1; #10;
    in =0; #10;
    in=1; #10;
    
    #20;

    $finish;

end

always @(posedge clk) begin
    $display("%4t | %b | %b | %b | %s | %s |",
    $time,rst,in,detected,
    (dut.current_state == 2'b00) ? "s0":
    (dut.current_state == 2'b01) ? "s1":
    (dut.current_state == 2'b10) ? "s10": "???",
    (dut.current_state == 2'b00) ? "idle":
    (dut.current_state == 2'b01) ? "saw 1":
    (dut.current_state == 2'b10) ? "saw 10": "unkown");

end
endmodule

vcd/squence_detector.vcd
$date
	Sun Apr  5 10:19:09 2026
$end
$version
	Icarus Verilog
$end
$timescale
	1s
$end
$scope module tb_squence_detector $end
$var wire 1 ! detected $end
$var reg 1 " clk $end
$var reg 1 # in $end
$var reg 1 $ rst $end
$scope module dut $end
$var wire 1 " clk $end
$var wire 1 # in $end
$var wire 1 $ rst $end
$var parameter 2 % s0 $end
$var parameter 2 & s1 $end
$var parameter 2 ' s10 $end
$var reg 2 ( current_state [1:0] $end
$var reg 1 ! detected $end
$var reg 2 ) next_state [1:0] $end
$upscope $end
$upscope $end
$enddefinitions $end
$comment Show the parameter values. $end
$dumpall
b10 '
b1 &
b0 %
$end
#0
$dumpvars
b0 )
b0 (
1$
0#
0"
0!
$end
#5
1"
#10
0"
0$
#15
1"
#20
0"
#25
1"
#30
b1 )
0"
1#
#35
b1 (
1"
#40
b10 )
0"
0#
#45
b0 )
b10 (
1"
#50
1!
b1 )
0"
1#
#55
0!
b1 (
1"
#60
b10 )
0"
0#
#65
b0 )
b10 (
1"
#70
1!
b1 )
0"
1#
#75
0!
b1 (
1"
#80
b10 )
0"
0#
#85
b0 )
b10 (
1"
#90
1!
b1 )
0"
1#
#95
0!
b1 (
1"
